Workbook

Sheet Tableau de Bord
A1: TABLEAU DE BORD DE GESTION - GARAGE MOTOCYCLES
A2: Indicateurs clés de performance (KPI), consolidation mensuelle du CA et suivi graphique.
A4: CHIFFRE D'AFFAIRES TOTAL TTC | D4: TOTAL TAXES COLLECTÉES (TVA 18%) | G4: TOTAL DES RÉPARATIONS | I4: PIÈCES EN ALERTE STOCK
A5: =SUM(Réparations!J5:J24) | D5: =SUM(Réparations!I5:I24) | G5: =COUNTA(Réparations!A5:A24) | I5: =COUNTIF('Stock & Pièces'!H5:H19,"RÉAPPROVISIONNER")
A7: ÉVOLUTION MENSUELLE DU CHIFFRE D'AFFAIRES (ANALYSE DÉTAILLÉE)
A8: Mois | B8: N° | C8: CA Pièces HT | D8: CA Main d'œuvre HT | E8: CA Total HT | F8: TVA (18%) | G8: CA Total TTC
A9: Janvier | B9: 1 | C9: =SUMIFS(Réparations!$F$5:$F$24, Réparations!$M$5:$M$24, B9) | D9: =SUMIFS(Réparations!$G$5:$G$24, Réparations!$M$5:$M$24, B9) | E9: =C9+D9 | F9: =E9*0.18 | G9: =E9+F9
A10: Février | B10: 2 | C10: =SUMIFS(Réparations!$F$5:$F$24, Réparations!$M$5:$M$24, B10) | D10: =SUMIFS(Réparations!$G$5:$G$24, Réparations!$M$5:$M$24, B10) | E10: =C10+D10 | F10: =E10*0.18 | G10: =E10+F10
A11: Mars | B11: 3 | C11: =SUMIFS(Réparations!$F$5:$F$24, Réparations!$M$5:$M$24, B11) | D11: =SUMIFS(Réparations!$G$5:$G$24, Réparations!$M$5:$M$24, B11) | E11: =C11+D11 | F11: =E11*0.18 | G11: =E11+F11
A12: Avril | B12: 4 | C12: =SUMIFS(Réparations!$F$5:$F$24, Réparations!$M$5:$M$24, B12) | D12: =SUMIFS(Réparations!$G$5:$G$24, Réparations!$M$5:$M$24, B12) | E12: =C12+D12 | F12: =E12*0.18 | G12: =E12+F12
A13: Mai | B13: 5 | C13: =SUMIFS(Réparations!$F$5:$F$24, Réparations!$M$5:$M$24, B13) | D13: =SUMIFS(Réparations!$G$5:$G$24, Réparations!$M$5:$M$24, B13) | E13: =C13+D13 | F13: =E13*0.18 | G13: =E13+F13
A14: Juin | B14: 6 | C14: =SUMIFS(Réparations!$F$5:$F$24, Réparations!$M$5:$M$24, B14) | D14: =SUMIFS(Réparations!$G$5:$G$24, Réparations!$M$5:$M$24, B14) | E14: =C14+D14 | F14: =E14*0.18 | G14: =E14+F14
A15: Juillet | B15: 7 | C15: =SUMIFS(Réparations!$F$5:$F$24, Réparations!$M$5:$M$24, B15) | D15: =SUMIFS(Réparations!$G$5:$G$24, Réparations!$M$5:$M$24, B15) | E15: =C15+D15 | F15: =E15*0.18 | G15: =E15+F15
A16: Août | B16: 8 | C16: =SUMIFS(Réparations!$F$5:$F$24, Réparations!$M$5:$M$24, B16) | D16: =SUMIFS(Réparations!$G$5:$G$24, Réparations!$M$5:$M$24, B16) | E16: =C16+D16 | F16: =E16*0.18 | G16: =E16+F16
A17: Septembre | B17: 9 | C17: =SUMIFS(Réparations!$F$5:$F$24, Réparations!$M$5:$M$24, B17) | D17: =SUMIFS(Réparations!$G$5:$G$24, Réparations!$M$5:$M$24, B17) | E17: =C17+D17 | F17: =E17*0.18 | G17: =E17+F17
A18: Octobre | B18: 10 | C18: =SUMIFS(Réparations!$F$5:$F$24, Réparations!$M$5:$M$24, B18) | D18: =SUMIFS(Réparations!$G$5:$G$24, Réparations!$M$5:$M$24, B18) | E18: =C18+D18 | F18: =E18*0.18 | G18: =E18+F18
A19: Novembre | B19: 11 | C19: =SUMIFS(Réparations!$F$5:$F$24, Réparations!$M$5:$M$24, B19) | D19: =SUMIFS(Réparations!$G$5:$G$24, Réparations!$M$5:$M$24, B19) | E19: =C19+D19 | F19: =E19*0.18 | G19: =E19+F19
A20: Décembre | B20: 12 | C20: =SUMIFS(Réparations!$F$5:$F$24, Réparations!$M$5:$M$24, B20) | D20: =SUMIFS(Réparations!$G$5:$G$24, Réparations!$M$5:$M$24, B20) | E20: =C20+D20 | F20: =E20*0.18 | G20: =E20+F20
A21: TOTAL ANNUEL | B21: 12 | C21: =SUM(C9:C20) | D21: =SUM(D9:D20) | E21: =SUM(E9:E20) | F21: =SUM(F9:F20) | G21: =SUM(G9:G20)

Sheet Clients & Véhicules
A1: RÉPERTOIRE DES CLIENTS
A2: Suivi des propriétaires, contacts et marques de motocycles prises en charge.
A4: ID Client | B4: Nom & Prénom | C4: Téléphone | D4: Adresse / Ville | E4: Marque Moto
A5: CLT-001 | B5: KOUASSI Yao Jean | C5: +225 07 48 12 34 56 | D5: Abidjan - Treichville | E5: Yamaha
A6: CLT-002 | B6: TRAORÉ Mamadou | C6: +225 05 64 22 19 80 | D6: Abidjan - Yopougon | E6: Bajaj
A7: CLT-003 | B7: DIABATÉ Ibrahima | C7: +225 01 77 90 45 11 | D7: Abidjan - Marcory | E7: Honda
A8: CLT-004 | B8: KONAN Affoué Sylvie | C8: +225 07 09 88 76 23 | D8: Abidjan - Cocody | E8: Yamaha
A9: CLT-005 | B9: BAKAYOKO Souleymane | C9: +225 05 55 43 21 00 | D9: Abidjan - Adjamé | E9: TVS
A10: CLT-006 | B10: SÉKA Gnangoran Guy | C10: +225 07 88 11 02 44 | D10: Abidjan - Koumassi | E10: Haojue
A11: CLT-007 | B11: N'GUESSAN Koffi Éric | C11: +225 01 40 23 88 95 | D11: Abidjan - Port-Bouët | E11: KTM
A12: CLT-008 | B12: OUÉDRAOGO Rasmané | C12: +225 05 12 67 94 33 | D12: Abidjan - Abobo | E12: Bajaj
A13: CLT-009 | B13: AMANI Brou Patrice | C13: +225 07 33 55 88 12 | D13: Abidjan - Plateau | E13: Yamaha
A14: CLT-010 | B14: ZOUZOUA Mireille | C14: +225 01 02 44 89 77 | D14: Abidjan - Cocody Riviera | E14: Honda

Sheet Stock & Pièces
A1: INVENTAIRE DU STOCK DE PIÈCES DÉTACHÉES
A2: Gestion des pièces, valorisation du stock au prix d'achat et alertes de réapprovisionnement.
A4: Réf Pièce | B4: Désignation | C4: Prix d'Achat HT | D4: Prix de Vente HT | E4: Quantité en Stock | F4: Stock Minimum | G4: Valeur du Stock HT | H4: Statut Stock
A5: PIEC-001 | B5: Huile Moteur 20W50 4T (Bidon 1L) | C5: 3500 | D5: 5500 | E5: 4 | F5: 10 | G5: =C5*E5 | H5: =IF(E5<=F5,"RÉAPPROVISIONNER","OK")
A6: PIEC-002 | B6: Bougie d'allumage standard (NGK C7HSA) | C6: 1200 | D6: 2500 | E6: 15 | F6: 10 | G6: =C6*E6 | H6: =IF(E6<=F6,"RÉAPPROVISIONNER","OK")
A7: PIEC-003 | B7: Kit Chaîne de transmission 428H | C7: 12000 | D7: 18500 | E7: 3 | F7: 5 | G7: =C7*E7 | H7: =IF(E7<=F7,"RÉAPPROVISIONNER","OK")
A8: PIEC-004 | B8: Plaquettes de frein avant à disque | C8: 3000 | D8: 6000 | E8: 8 | F8: 6 | G8: =C8*E8 | H8: =IF(E8<=F8,"RÉAPPROVISIONNER","OK")
A9: PIEC-005 | B9: Mâchoires de frein arrière à tambour | C9: 2500 | D9: 5000 | E9: 2 | F9: 5 | G9: =C9*E9 | H9: =IF(E9<=F9,"RÉAPPROVISIONNER","OK")
A10: PIEC-006 | B10: Pneu Arrière Renforcé 3.00-17 | C10: 14000 | D10: 22000 | E10: 6 | F10: 4 | G10: =C10*E10 | H10: =IF(E10<=F10,"RÉAPPROVISIONNER","OK")
A11: PIEC-007 | B11: Chambre à air renforcée 2.75/3.00-17 | C11: 2000 | D11: 3500 | E11: 18 | F11: 8 | G11: =C11*E11 | H11: =IF(E11<=F11,"RÉAPPROVISIONNER","OK")
A12: PIEC-008 | B12: Câble d'embrayage renforcé | C12: 1500 | D12: 3000 | E12: 7 | F12: 5 | G12: =C12*E12 | H12: =IF(E12<=F12,"RÉAPPROVISIONNER","OK")
A13: PIEC-009 | B13: Câble de frein avant | C13: 1500 | D13: 3000 | E13: 3 | F13: 5 | G13: =C13*E13 | H13: =IF(E13<=F13,"RÉAPPROVISIONNER","OK")
A14: PIEC-010 | B14: Filtre à air mousse haute filtration | C14: 1800 | D14: 3500 | E14: 12 | F14: 6 | G14: =C14*E14 | H14: =IF(E14<=F14,"RÉAPPROVISIONNER","OK")
A15: PIEC-011 | B15: Batterie 12V 5Ah sans entretien | C15: 11000 | D15: 17000 | E15: 2 | F15: 4 | G15: =C15*E15 | H15: =IF(E15<=F15,"RÉAPPROVISIONNER","OK")
A16: PIEC-012 | B16: Ampoule Phare LED H4 12V | C16: 2500 | D16: 5000 | E16: 9 | F16: 5 | G16: =C16*E16 | H16: =IF(E16<=F16,"RÉAPPROVISIONNER","OK")
... A19: PIEC-015 | B19: Carburateur standard complet 125cc | C19: 15000 | D19: 24000 | E19: 2 | F19: 3 | G19: =C19*E19 | H19: =IF(E19<=F19,"RÉAPPROVISIONNER","OK")
B20: TOTAL VALEUR DU STOCK | E20: =SUM(E5:E19) | G20: =SUM(G5:G19)

Sheet Réparations
A1: REGISTRE DES RÉPARATIONS & ORDRES DE SERVICE
A2: Journal des interventions d'atelier, facturation HT/TVA/TTC et modes de règlement.
A4: N° Fiche | B4: Date | C4: Client | D4: Véhicule / Immat | E4: Description Intervention | F4: Total Pièces HT | G4: Main d'œuvre HT | H4: Total HT | I4: TVA 18% | J4: Total TTC | K4: Mode Paiement | L4: Statut Paiement | M4: N° Mois
A5: OR-2026-001 | B5: 46030 | C5: KOUASSI Yao Jean | D5: Yamaha Crypton (AB-4589-CI) | E5: Vidange complète + Remplacement bougie | F5: 8000 | G5: 5000 | H5: =F5+G5 | I5: =H5*0.18 | J5: =H5+I5 | K5: Mobile Money | L5: Payé | M5: =MONTH(B5)
A6: OR-2026-002 | B6: 46043 | C6: TRAORÉ Mamadou | D6: Bajaj Boxer 150 (AB-9102-CI) | E6: Changement kit chaîne + réglage carbu | F6: 18500 | G6: 7500 | H6: =F6+G6 | I6: =H6*0.18 | J6: =H6+I6 | K6: Espèces | L6: Payé | M6: =MONTH(B6)
A7: OR-2026-003 | B7: 46058 | C7: DIABATÉ Ibrahima | D7: Honda Ace 110 (AB-3312-CI) | E7: Remplacement pneu arrière + chambre à air | F7: 25500 | G7: 6000 | H7: =F7+G7 | I7: =H7*0.18 | J7: =H7+I7 | K7: Mobile Money | L7: Payé | M7: =MONTH(B7)
A8: OR-2026-004 | B8: 46071 | C8: KONAN Affoué Sylvie | D8: Yamaha NMAX 155 (AB-7721-CI) | E8: Plaquettes frein AV + révision transmission | F8: 12000 | G8: 10000 | H8: =F8+G8 | I8: =H8*0.18 | J8: =H8+I8 | K8: Virement | L8: Payé | M8: =MONTH(B8)
A9: OR-2026-005 | B9: 46091 | C9: BAKAYOKO Souleymane | D9: TVS Apache 160 (AB-2144-CI) | E9: Batterie neuve + remplacement ampoule LED | F9: 22000 | G9: 4500 | H9: =F9+G9 | I9: =H9*0.18 | J9: =H9+I9 | K9: Mobile Money | L9: Payé | M9: =MONTH(B9)
A10: OR-2026-006 | B10: 46108 | C10: SÉKA Gnangoran Guy | D10: Haojue Lucky 110 (AB-6650-CI) | E10: Câble frein + mâchoires arrière + filtre | F10: 11500 | G10: 6500 | H10: =F10+G10 | I10: =H10*0.18 | J10: =H10+I10 | K10: Espèces | L10: Payé | M10: =MONTH(B10)
A11: OR-2026-007 | B11: 46124 | C11: N'GUESSAN Koffi Éric | D11: KTM Duke 200 (AB-1189-CI) | E11: Changement amortisseurs + vidange synthèse | F11: 33500 | G11: 15000 | H11: =F11+G11 | I11: =H11*0.18 | J11: =H11+I11 | K11: Mobile Money | L11: Payé | M11: =MONTH(B11)
A12: OR-2026-008 | B12: 46137 | C12: OUÉDRAOGO Rasmané | D12: Bajaj Pulsar 180 (AB-5431-CI) | E12: Remplacement carburateur + câble embrayage | F12: 27000 | G12: 8000 | H12: =F12+G12 | I12: =H12*0.18 | J12: =H12+I12 | K12: Espèces | L12: Payé | M12: =MONTH(B12)
A13: OR-2026-009 | B13: 46151 | C13: AMANI Brou Patrice | D13: Yamaha DT 125 (AB-8809-CI) | E13: Réfection haut moteur + joint culasse | F13: 38000 | G13: 20000 | H13: =F13+G13 | I13: =H13*0.18 | J13: =H13+I13 | K13: Mobile Money | L13: Payé | M13: =MONTH(B13)
A14: OR-2026-010 | B14: 46164 | C14: ZOUZOUA Mireille | D14: Honda Wave 110i (AB-9923-CI) | E14: Plaquettes AV + vidange + bougie | F14: 14000 | G14: 6000 | H14: =F14+G14 | I14: =H14*0.18 | J14: =H14+I14 | K14: Mobile Money | L14: Payé | M14: =MONTH(B14)
A15: OR-2026-011 | B15: 46180 | C15: KOUASSI Yao Jean | D15: Yamaha Crypton (AB-4589-CI) | E15: Kit chaîne transmission + pneu AR | F15: 40500 | G15: 9000 | H15: =F15+G15 | I15: =H15*0.18 | J15: =H15+I15 | K15: Mobile Money | L15: Payé | M15: =MONTH(B15)
A16: OR-2026-012 | B16: 46202 | C16: TRAORÉ Mamadou | D16: Bajaj Boxer 150 (AB-9102-CI) | E16: Vidange + tambour frein AR + filtre à air | F16: 14000 | G16: 6000 | H16: =F16+G16 | I16: =H16*0.18 | J16: =H16+I16 | K16: Espèces | L16: Payé | M16: =MONTH(B16)
... A24: OR-2026-020 | B24: 46374 | C24: ZOUZOUA Mireille | D24: Honda Wave 110i (AB-9923-CI) | E24: Grande révision annuelle + 2 pneus neufs | F24: 48000 | G24: 15000 | H24: =F24+G24 | I24: =H24*0.18 | J24: =H24+I24 | K24: Mobile Money | L24: Payé | M24: =MONTH(B24)
E25: TOTAL GÉNÉRAL | F25: =SUM(F5:F24) | G25: =SUM(G5:G24) | H25: =SUM(H5:H24) | I25: =SUM(I5:I24) | J25: =SUM(J5:J24)
